[
    {
        "id": 110001,
        "activityId": 11104,
        "isOnline": 1,
        "minType": "雷米特杯成就任务",
        "name": "",
        "desc": "通过TRC-1[故事]难度",
        "needAccept": 1,
        "bonusMail": 0,
        "params": "",
        "openLimit": "",
        "listenerType": "EpisodeFinish",
        "listenerParam": "1110101",
        "maxProgress": 1,
        "maxFinishCount": 1,
        "activity": 1,
        "jumpId": 41110101,
        "bonus": ""
    },
    {
        "id": 110002,
        "activityId": 11104,
        "isOnline": 1,
        "minType": "雷米特杯成就任务",
        "name": "",
        "desc": "通过TRC-2[故事]难度",
        "needAccept": 1,
        "bonusMail": 0,
        "params": "",
        "openLimit": "",
        "listenerType": "EpisodeFinish",
        "listenerParam": "1110102",
        "maxProgress": 1,
        "maxFinishCount": 1,
        "activity": 1,
        "jumpId": 41110102,
        "bonus": ""
    },
    {
        "id": 110003,
        "activityId": 11104,
        "isOnline": 1,
        "minType": "雷米特杯成就任务",
        "name": "",
        "desc": "通过TRC-4[故事]难度",
        "needAccept": 1,
        "bonusMail": 0,
        "params": "",
        "openLimit": "",
        "listenerType": "EpisodeFinish",
        "listenerParam": "1110104",
        "maxProgress": 1,
        "maxFinishCount": 1,
        "activity": 1,
        "jumpId": 41110104,
        "bonus": ""
    },
    {
        "id": 110004,
        "activityId": 11104,
        "isOnline": 1,
        "minType": "雷米特杯成就任务",
        "name": "",
        "desc": "通过TRC-5[故事]难度",
        "needAccept": 1,
        "bonusMail": 0,
        "params": "",
        "openLimit": "",
        "listenerType": "EpisodeFinish",
        "listenerParam": "1110105",
        "maxProgress": 1,
        "maxFinishCount": 1,
        "activity": 1,
        "jumpId": 41110105,
        "bonus": ""
    },
    {
        "id": 110005,
        "activityId": 11104,
        "isOnline": 1,
        "minType": "雷米特杯成就任务",
        "name": "",
        "desc": "通过TRC-7[故事]难度",
        "needAccept": 1,
        "bonusMail": 0,
        "params": "",
        "openLimit": "",
        "listenerType": "EpisodeFinish",
        "listenerParam": "1110107",
        "maxProgress": 1,
        "maxFinishCount": 1,
        "activity": 1,
        "jumpId": 41110107,
        "bonus": ""
    },
    {
        "id": 110006,
        "activityId": 11104,
        "isOnline": 1,
        "minType": "雷米特杯成就任务",
        "name": "",
        "desc": "通过TRC-8[故事]难度",
        "needAccept": 1,
        "bonusMail": 0,
        "params": "",
        "openLimit": "",
        "listenerType": "EpisodeFinish",
        "listenerParam": "1110108",
        "maxProgress": 1,
        "maxFinishCount": 1,
        "activity": 1,
        "jumpId": 41110108,
        "bonus": ""
    },
    {
        "id": 110007,
        "activityId": 11104,
        "isOnline": 1,
        "minType": "雷米特杯成就任务",
        "name": "",
        "desc": "通过TRC-9[故事]难度",
        "needAccept": 1,
        "bonusMail": 0,
        "params": "",
        "openLimit": "",
        "listenerType": "EpisodeFinish",
        "listenerParam": "1110109",
        "maxProgress": 1,
        "maxFinishCount": 1,
        "activity": 1,
        "jumpId": 41110109,
        "bonus": ""
    },
    {
        "id": 110008,
        "activityId": 11104,
        "isOnline": 1,
        "minType": "雷米特杯成就任务",
        "name": "",
        "desc": "通过TRC-11[故事]难度",
        "needAccept": 1,
        "bonusMail": 0,
        "params": "",
        "openLimit": "",
        "listenerType": "EpisodeFinish",
        "listenerParam": "1110111",
        "maxProgress": 1,
        "maxFinishCount": 1,
        "activity": 1,
        "jumpId": 41110111,
        "bonus": ""
    },
    {
        "id": 110009,
        "activityId": 11104,
        "isOnline": 1,
        "minType": "雷米特杯成就任务",
        "name": "",
        "desc": "通过TRC-12[故事]难度",
        "needAccept": 1,
        "bonusMail": 0,
        "params": "",
        "openLimit": "",
        "listenerType": "EpisodeFinish",
        "listenerParam": "1110112",
        "maxProgress": 1,
        "maxFinishCount": 1,
        "activity": 1,
        "jumpId": 41110112,
        "bonus": ""
    },
    {
        "id": 110010,
        "activityId": 11104,
        "isOnline": 1,
        "minType": "雷米特杯成就任务",
        "name": "",
        "desc": "通过TRC-13[故事]难度",
        "needAccept": 1,
        "bonusMail": 0,
        "params": "",
        "openLimit": "",
        "listenerType": "EpisodeFinish",
        "listenerParam": "1110113",
        "maxProgress": 1,
        "maxFinishCount": 1,
        "activity": 1,
        "jumpId": 41110113,
        "bonus": ""
    },
    {
        "id": 110011,
        "activityId": 11104,
        "isOnline": 1,
        "minType": "雷米特杯成就任务",
        "name": "",
        "desc": "通过TRC-14[故事]难度",
        "needAccept": 1,
        "bonusMail": 0,
        "params": "",
        "openLimit": "",
        "listenerType": "EpisodeFinish",
        "listenerParam": "1110114",
        "maxProgress": 1,
        "maxFinishCount": 1,
        "activity": 1,
        "jumpId": 41110114,
        "bonus": ""
    },
    {
        "id": 110012,
        "activityId": 11104,
        "isOnline": 1,
        "minType": "雷米特杯成就任务",
        "name": "",
        "desc": "完成报纸解密-丢失的字符之一",
        "needAccept": 1,
        "bonusMail": 0,
        "params": "",
        "openLimit": "",
        "listenerType": "ChapterMapElement",
        "listenerParam": "11101061",
        "maxProgress": 1,
        "maxFinishCount": 1,
        "activity": 1,
        "jumpId": 10011105,
        "bonus": ""
    },
    {
        "id": 110013,
        "activityId": 11104,
        "isOnline": 1,
        "minType": "雷米特杯成就任务",
        "name": "",
        "desc": "完成报纸解密-丢失的字符之二",
        "needAccept": 1,
        "bonusMail": 0,
        "params": "",
        "openLimit": "",
        "listenerType": "ChapterMapElement",
        "listenerParam": "11101091",
        "maxProgress": 1,
        "maxFinishCount": 1,
        "activity": 1,
        "jumpId": 10011105,
        "bonus": ""
    },
    {
        "id": 110014,
        "activityId": 11104,
        "isOnline": 1,
        "minType": "雷米特杯成就任务",
        "name": "",
        "desc": "完成报纸解密-丢失的字符之三",
        "needAccept": 1,
        "bonusMail": 0,
        "params": "",
        "openLimit": "",
        "listenerType": "ChapterMapElement",
        "listenerParam": "11101161",
        "maxProgress": 1,
        "maxFinishCount": 1,
        "activity": 1,
        "jumpId": 10011105,
        "bonus": ""
    },
    {
        "id": 110015,
        "activityId": 11104,
        "isOnline": 1,
        "minType": "雷米特杯成就任务",
        "name": "",
        "desc": "收集到3张花边新闻",
        "needAccept": 1,
        "bonusMail": 0,
        "params": "",
        "openLimit": "",
        "listenerType": "ChapterMapElement",
        "listenerParam": "11101011#11101031#11101041#11101051#11101071#11101121#11101131#11101141",
        "maxProgress": 3,
        "maxFinishCount": 1,
        "activity": 1,
        "jumpId": 10011105,
        "bonus": ""
    },
    {
        "id": 110016,
        "activityId": 11104,
        "isOnline": 1,
        "minType": "雷米特杯成就任务",
        "name": "",
        "desc": "收集到8张花边新闻",
        "needAccept": 1,
        "bonusMail": 0,
        "params": "",
        "openLimit": "",
        "listenerType": "ChapterMapElement",
        "listenerParam": "11101011#11101031#11101041#11101051#11101071#11101121#11101131#11101141",
        "maxProgress": 8,
        "maxFinishCount": 1,
        "activity": 1,
        "jumpId": 10011105,
        "bonus": ""
    },
    {
        "id": 110017,
        "activityId": 11104,
        "isOnline": 1,
        "minType": "雷米特杯成就任务",
        "name": "",
        "desc": "通过TRC-4[意外]难度",
        "needAccept": 1,
        "bonusMail": 0,
        "params": "",
        "openLimit": "",
        "listenerType": "EpisodeFinish",
        "listenerParam": "1130101",
        "maxProgress": 1,
        "maxFinishCount": 1,
        "activity": 1,
        "jumpId": 41130101,
        "bonus": ""
    },
    {
        "id": 110018,
        "activityId": 11104,
        "isOnline": 1,
        "minType": "雷米特杯成就任务",
        "name": "",
        "desc": "通过TRC-4[艰难]难度",
        "needAccept": 1,
        "bonusMail": 0,
        "params": "",
        "openLimit": "",
        "listenerType": "EpisodeFinish",
        "listenerParam": "1140101",
        "maxProgress": 1,
        "maxFinishCount": 1,
        "activity": 1,
        "jumpId": 41140101,
        "bonus": ""
    },
    {
        "id": 110019,
        "activityId": 11104,
        "isOnline": 1,
        "minType": "雷米特杯成就任务",
        "name": "",
        "desc": "通过TRC-8[意外]难度",
        "needAccept": 1,
        "bonusMail": 0,
        "params": "",
        "openLimit": "",
        "listenerType": "EpisodeFinish",
        "listenerParam": "1130102",
        "maxProgress": 1,
        "maxFinishCount": 1,
        "activity": 1,
        "jumpId": 41130102,
        "bonus": ""
    },
    {
        "id": 110020,
        "activityId": 11104,
        "isOnline": 1,
        "minType": "雷米特杯成就任务",
        "name": "",
        "desc": "通过TRC-8[艰难]难度",
        "needAccept": 1,
        "bonusMail": 0,
        "params": "",
        "openLimit": "",
        "listenerType": "EpisodeFinish",
        "listenerParam": "1140102",
        "maxProgress": 1,
        "maxFinishCount": 1,
        "activity": 1,
        "jumpId": 41140102,
        "bonus": ""
    },
    {
        "id": 110021,
        "activityId": 11104,
        "isOnline": 1,
        "minType": "雷米特杯成就任务",
        "name": "",
        "desc": "通过TRC-12[意外]难度",
        "needAccept": 1,
        "bonusMail": 0,
        "params": "",
        "openLimit": "",
        "listenerType": "EpisodeFinish",
        "listenerParam": "1130103",
        "maxProgress": 1,
        "maxFinishCount": 1,
        "activity": 1,
        "jumpId": 41130103,
        "bonus": ""
    },
    {
        "id": 110022,
        "activityId": 11104,
        "isOnline": 1,
        "minType": "雷米特杯成就任务",
        "name": "",
        "desc": "通过TRC-12[艰难]难度",
        "needAccept": 1,
        "bonusMail": 0,
        "params": "",
        "openLimit": "",
        "listenerType": "EpisodeFinish",
        "listenerParam": "1140103",
        "maxProgress": 1,
        "maxFinishCount": 1,
        "activity": 1,
        "jumpId": 41140103,
        "bonus": ""
    },
    {
        "id": 110023,
        "activityId": 11104,
        "isOnline": 1,
        "minType": "雷米特杯成就任务",
        "name": "",
        "desc": "通过TRC-14[意外]难度",
        "needAccept": 1,
        "bonusMail": 0,
        "params": "",
        "openLimit": "",
        "listenerType": "EpisodeFinish",
        "listenerParam": "1130104",
        "maxProgress": 1,
        "maxFinishCount": 1,
        "activity": 1,
        "jumpId": 41130104,
        "bonus": ""
    },
    {
        "id": 110024,
        "activityId": 11104,
        "isOnline": 1,
        "minType": "雷米特杯成就任务",
        "name": "",
        "desc": "通过TRC-14[艰难]难度",
        "needAccept": 1,
        "bonusMail": 0,
        "params": "",
        "openLimit": "",
        "listenerType": "EpisodeFinish",
        "listenerParam": "1140104",
        "maxProgress": 1,
        "maxFinishCount": 1,
        "activity": 1,
        "jumpId": 41140104,
        "bonus": ""
    },
    {
        "id": 110025,
        "activityId": 11104,
        "isOnline": 1,
        "minType": "雷米特杯成就任务",
        "name": "",
        "desc": "击败100个安保机器人",
        "needAccept": 1,
        "bonusMail": 0,
        "params": "",
        "openLimit": "",
        "listenerType": "KillRace",
        "listenerParam": "chapterTypes=111#112#113#114,race=4",
        "maxProgress": 100,
        "maxFinishCount": 1,
        "activity": 1,
        "jumpId": 10011105,
        "bonus": ""
    },
    {
        "id": 110026,
        "activityId": 11104,
        "isOnline": 1,
        "minType": "雷米特杯成就任务",
        "name": "",
        "desc": "击败200个安保机器人",
        "needAccept": 1,
        "bonusMail": 0,
        "params": "",
        "openLimit": "",
        "listenerType": "KillRace",
        "listenerParam": "chapterTypes=111#112#113#114,race=4",
        "maxProgress": 200,
        "maxFinishCount": 1,
        "activity": 1,
        "jumpId": 10011105,
        "bonus": ""
    },
    {
        "id": 110027,
        "activityId": 11104,
        "isOnline": 1,
        "minType": "雷米特杯成就任务",
        "name": "",
        "desc": "击败300个安保机器人",
        "needAccept": 1,
        "bonusMail": 0,
        "params": "",
        "openLimit": "",
        "listenerType": "KillRace",
        "listenerParam": "chapterTypes=111#112#113#114,race=4",
        "maxProgress": 300,
        "maxFinishCount": 1,
        "activity": 1,
        "jumpId": 10011105,
        "bonus": ""
    },
    {
        "id": 110028,
        "activityId": 11104,
        "isOnline": 1,
        "minType": "雷米特杯成就任务",
        "name": "",
        "desc": "击败400个安保机器人",
        "needAccept": 1,
        "bonusMail": 0,
        "params": "",
        "openLimit": "",
        "listenerType": "KillRace",
        "listenerParam": "chapterTypes=111#112#113#114,race=4",
        "maxProgress": 400,
        "maxFinishCount": 1,
        "activity": 2,
        "jumpId": 10011105,
        "bonus": ""
    },
    {
        "id": 110029,
        "activityId": 11104,
        "isOnline": 1,
        "minType": "雷米特杯成就任务",
        "name": "",
        "desc": "累积击败50个敌人",
        "needAccept": 1,
        "bonusMail": 0,
        "params": "",
        "openLimit": "",
        "listenerType": "ChapterTypeKill",
        "listenerParam": "111#112#113#114",
        "maxProgress": 50,
        "maxFinishCount": 1,
        "activity": 1,
        "jumpId": 10011105,
        "bonus": ""
    },
    {
        "id": 110030,
        "activityId": 11104,
        "isOnline": 1,
        "minType": "雷米特杯成就任务",
        "name": "",
        "desc": "累积击败100个敌人",
        "needAccept": 1,
        "bonusMail": 0,
        "params": "",
        "openLimit": "",
        "listenerType": "ChapterTypeKill",
        "listenerParam": "111#112#113#114",
        "maxProgress": 100,
        "maxFinishCount": 1,
        "activity": 1,
        "jumpId": 10011105,
        "bonus": ""
    },
    {
        "id": 110031,
        "activityId": 11104,
        "isOnline": 1,
        "minType": "雷米特杯成就任务",
        "name": "",
        "desc": "累积击败300个敌人",
        "needAccept": 1,
        "bonusMail": 0,
        "params": "",
        "openLimit": "",
        "listenerType": "ChapterTypeKill",
        "listenerParam": "111#112#113#114",
        "maxProgress": 300,
        "maxFinishCount": 1,
        "activity": 1,
        "jumpId": 10011105,
        "bonus": ""
    },
    {
        "id": 110032,
        "activityId": 11104,
        "isOnline": 1,
        "minType": "雷米特杯成就任务",
        "name": "",
        "desc": "累积击败500个敌人",
        "needAccept": 1,
        "bonusMail": 0,
        "params": "",
        "openLimit": "",
        "listenerType": "ChapterTypeKill",
        "listenerParam": "111#112#113#114",
        "maxProgress": 500,
        "maxFinishCount": 1,
        "activity": 2,
        "jumpId": 10011105,
        "bonus": ""
    },
    {
        "id": 110033,
        "activityId": 11104,
        "isOnline": 1,
        "minType": "雷米特杯成就任务",
        "name": "",
        "desc": "通过活动关卡30次",
        "needAccept": 1,
        "bonusMail": 0,
        "params": "",
        "openLimit": "",
        "listenerType": "DungeonPass",
        "listenerParam": "111#112#113#114",
        "maxProgress": 30,
        "maxFinishCount": 1,
        "activity": 1,
        "jumpId": 10011105,
        "bonus": ""
    },
    {
        "id": 110034,
        "activityId": 11104,
        "isOnline": 1,
        "minType": "雷米特杯成就任务",
        "name": "",
        "desc": "通过活动关卡60次",
        "needAccept": 1,
        "bonusMail": 0,
        "params": "",
        "openLimit": "",
        "listenerType": "DungeonPass",
        "listenerParam": "111#112#113#114",
        "maxProgress": 60,
        "maxFinishCount": 1,
        "activity": 1,
        "jumpId": 10011105,
        "bonus": ""
    },
    {
        "id": 110035,
        "activityId": 11104,
        "isOnline": 1,
        "minType": "雷米特杯成就任务",
        "name": "",
        "desc": "通过活动关卡90次",
        "needAccept": 1,
        "bonusMail": 0,
        "params": "",
        "openLimit": "",
        "listenerType": "DungeonPass",
        "listenerParam": "111#112#113#114",
        "maxProgress": 90,
        "maxFinishCount": 1,
        "activity": 2,
        "jumpId": 10011105,
        "bonus": ""
    },
    {
        "id": 110036,
        "activityId": 11104,
        "isOnline": 1,
        "minType": "雷米特杯成就任务",
        "name": "",
        "desc": "通过活动关卡120次",
        "needAccept": 1,
        "bonusMail": 0,
        "params": "",
        "openLimit": "",
        "listenerType": "DungeonPass",
        "listenerParam": "111#112#113#114",
        "maxProgress": 120,
        "maxFinishCount": 1,
        "activity": 2,
        "jumpId": 10011105,
        "bonus": ""
    },
    {
        "id": 110037,
        "activityId": 11104,
        "isOnline": 1,
        "minType": "雷米特杯成就任务",
        "name": "",
        "desc": "消耗5000个帕帕币",
        "needAccept": 1,
        "bonusMail": 0,
        "params": "",
        "openLimit": "",
        "listenerType": "CurrencyDec",
        "listenerParam": "111",
        "maxProgress": 5000,
        "maxFinishCount": 1,
        "activity": 1,
        "jumpId": 10011112,
        "bonus": ""
    },
    {
        "id": 110038,
        "activityId": 11104,
        "isOnline": 1,
        "minType": "雷米特杯成就任务",
        "name": "",
        "desc": "消耗20000个帕帕币",
        "needAccept": 1,
        "bonusMail": 0,
        "params": "",
        "openLimit": "",
        "listenerType": "CurrencyDec",
        "listenerParam": "111",
        "maxProgress": 20000,
        "maxFinishCount": 1,
        "activity": 2,
        "jumpId": 10011112,
        "bonus": ""
    },
    {
        "id": 110039,
        "activityId": 11104,
        "isOnline": 1,
        "minType": "雷米特杯成就任务",
        "name": "",
        "desc": "通过TRC-1[危机]难度",
        "needAccept": 1,
        "bonusMail": 0,
        "params": "",
        "openLimit": "",
        "listenerType": "EpisodeFinish",
        "listenerParam": "1120101",
        "maxProgress": 1,
        "maxFinishCount": 1,
        "activity": 1,
        "jumpId": 41120101,
        "bonus": ""
    },
    {
        "id": 110040,
        "activityId": 11104,
        "isOnline": 1,
        "minType": "雷米特杯成就任务",
        "name": "",
        "desc": "通过TRC-2[危机]难度",
        "needAccept": 1,
        "bonusMail": 0,
        "params": "",
        "openLimit": "",
        "listenerType": "EpisodeFinish",
        "listenerParam": "1120102",
        "maxProgress": 1,
        "maxFinishCount": 1,
        "activity": 1,
        "jumpId": 41120102,
        "bonus": ""
    },
    {
        "id": 110041,
        "activityId": 11104,
        "isOnline": 1,
        "minType": "雷米特杯成就任务",
        "name": "",
        "desc": "通过TRC-4[危机]难度",
        "needAccept": 1,
        "bonusMail": 0,
        "params": "",
        "openLimit": "",
        "listenerType": "EpisodeFinish",
        "listenerParam": "1120104",
        "maxProgress": 1,
        "maxFinishCount": 1,
        "activity": 1,
        "jumpId": 41120104,
        "bonus": ""
    },
    {
        "id": 110042,
        "activityId": 11104,
        "isOnline": 1,
        "minType": "雷米特杯成就任务",
        "name": "",
        "desc": "通过TRC-5[危机]难度",
        "needAccept": 1,
        "bonusMail": 0,
        "params": "",
        "openLimit": "",
        "listenerType": "EpisodeFinish",
        "listenerParam": "1120105",
        "maxProgress": 1,
        "maxFinishCount": 1,
        "activity": 1,
        "jumpId": 41120105,
        "bonus": ""
    },
    {
        "id": 110043,
        "activityId": 11104,
        "isOnline": 1,
        "minType": "雷米特杯成就任务",
        "name": "",
        "desc": "通过TRC-7[危机]难度",
        "needAccept": 1,
        "bonusMail": 0,
        "params": "",
        "openLimit": "",
        "listenerType": "EpisodeFinish",
        "listenerParam": "1120107",
        "maxProgress": 1,
        "maxFinishCount": 1,
        "activity": 1,
        "jumpId": 41120107,
        "bonus": ""
    },
    {
        "id": 110044,
        "activityId": 11104,
        "isOnline": 1,
        "minType": "雷米特杯成就任务",
        "name": "",
        "desc": "通过TRC-8[危机]难度",
        "needAccept": 1,
        "bonusMail": 0,
        "params": "",
        "openLimit": "",
        "listenerType": "EpisodeFinish",
        "listenerParam": "1120108",
        "maxProgress": 1,
        "maxFinishCount": 1,
        "activity": 1,
        "jumpId": 41120108,
        "bonus": ""
    },
    {
        "id": 110045,
        "activityId": 11104,
        "isOnline": 1,
        "minType": "雷米特杯成就任务",
        "name": "",
        "desc": "通过TRC-9[危机]难度",
        "needAccept": 1,
        "bonusMail": 0,
        "params": "",
        "openLimit": "",
        "listenerType": "EpisodeFinish",
        "listenerParam": "1120109",
        "maxProgress": 1,
        "maxFinishCount": 1,
        "activity": 1,
        "jumpId": 41120109,
        "bonus": ""
    },
    {
        "id": 110046,
        "activityId": 11104,
        "isOnline": 1,
        "minType": "雷米特杯成就任务",
        "name": "",
        "desc": "通过TRC-11[危机]难度",
        "needAccept": 1,
        "bonusMail": 0,
        "params": "",
        "openLimit": "",
        "listenerType": "EpisodeFinish",
        "listenerParam": "1120111",
        "maxProgress": 1,
        "maxFinishCount": 1,
        "activity": 1,
        "jumpId": 41120111,
        "bonus": ""
    },
    {
        "id": 110047,
        "activityId": 11104,
        "isOnline": 1,
        "minType": "雷米特杯成就任务",
        "name": "",
        "desc": "通过TRC-12[危机]难度",
        "needAccept": 1,
        "bonusMail": 0,
        "params": "",
        "openLimit": "",
        "listenerType": "EpisodeFinish",
        "listenerParam": "1120112",
        "maxProgress": 1,
        "maxFinishCount": 1,
        "activity": 1,
        "jumpId": 41120112,
        "bonus": ""
    },
    {
        "id": 110048,
        "activityId": 11104,
        "isOnline": 1,
        "minType": "雷米特杯成就任务",
        "name": "",
        "desc": "通过TRC-13[危机]难度",
        "needAccept": 1,
        "bonusMail": 0,
        "params": "",
        "openLimit": "",
        "listenerType": "EpisodeFinish",
        "listenerParam": "1120113",
        "maxProgress": 1,
        "maxFinishCount": 1,
        "activity": 1,
        "jumpId": 41120113,
        "bonus": ""
    },
    {
        "id": 110049,
        "activityId": 11104,
        "isOnline": 1,
        "minType": "雷米特杯成就任务",
        "name": "",
        "desc": "通过TRC-14[危机]难度",
        "needAccept": 1,
        "bonusMail": 0,
        "params": "",
        "openLimit": "",
        "listenerType": "EpisodeFinish",
        "listenerParam": "1120114",
        "maxProgress": 1,
        "maxFinishCount": 1,
        "activity": 1,
        "jumpId": 41120114,
        "bonus": ""
    },
    {
        "id": 110050,
        "activityId": 11104,
        "isOnline": 1,
        "minType": "雷米特杯成就任务",
        "name": "",
        "desc": "2星评价通过TRC-1[危机]难度",
        "needAccept": 1,
        "bonusMail": 0,
        "params": "",
        "openLimit": "",
        "listenerType": "EpisodeStarAdvence",
        "listenerParam": "1120101",
        "maxProgress": 1,
        "maxFinishCount": 1,
        "activity": 1,
        "jumpId": 41120101,
        "bonus": ""
    },
    {
        "id": 110051,
        "activityId": 11104,
        "isOnline": 1,
        "minType": "雷米特杯成就任务",
        "name": "",
        "desc": "2星评价通过TRC-2[危机]难度",
        "needAccept": 1,
        "bonusMail": 0,
        "params": "",
        "openLimit": "",
        "listenerType": "EpisodeStarAdvence",
        "listenerParam": "1120102",
        "maxProgress": 1,
        "maxFinishCount": 1,
        "activity": 1,
        "jumpId": 41120102,
        "bonus": ""
    },
    {
        "id": 110052,
        "activityId": 11104,
        "isOnline": 1,
        "minType": "雷米特杯成就任务",
        "name": "",
        "desc": "2星评价通过TRC-4[危机]难度",
        "needAccept": 1,
        "bonusMail": 0,
        "params": "",
        "openLimit": "",
        "listenerType": "EpisodeStarAdvence",
        "listenerParam": "1120104",
        "maxProgress": 1,
        "maxFinishCount": 1,
        "activity": 1,
        "jumpId": 41120104,
        "bonus": ""
    },
    {
        "id": 110053,
        "activityId": 11104,
        "isOnline": 1,
        "minType": "雷米特杯成就任务",
        "name": "",
        "desc": "2星评价通过TRC-5[危机]难度",
        "needAccept": 1,
        "bonusMail": 0,
        "params": "",
        "openLimit": "",
        "listenerType": "EpisodeStarAdvence",
        "listenerParam": "1120105",
        "maxProgress": 1,
        "maxFinishCount": 1,
        "activity": 1,
        "jumpId": 41120105,
        "bonus": ""
    },
    {
        "id": 110054,
        "activityId": 11104,
        "isOnline": 1,
        "minType": "雷米特杯成就任务",
        "name": "",
        "desc": "2星评价通过TRC-7[危机]难度",
        "needAccept": 1,
        "bonusMail": 0,
        "params": "",
        "openLimit": "",
        "listenerType": "EpisodeStarAdvence",
        "listenerParam": "1120107",
        "maxProgress": 1,
        "maxFinishCount": 1,
        "activity": 1,
        "jumpId": 41120107,
        "bonus": ""
    },
    {
        "id": 110055,
        "activityId": 11104,
        "isOnline": 1,
        "minType": "雷米特杯成就任务",
        "name": "",
        "desc": "2星评价通过TRC-8[危机]难度",
        "needAccept": 1,
        "bonusMail": 0,
        "params": "",
        "openLimit": "",
        "listenerType": "EpisodeStarAdvence",
        "listenerParam": "1120108",
        "maxProgress": 1,
        "maxFinishCount": 1,
        "activity": 1,
        "jumpId": 41120108,
        "bonus": ""
    },
    {
        "id": 110056,
        "activityId": 11104,
        "isOnline": 1,
        "minType": "雷米特杯成就任务",
        "name": "",
        "desc": "2星评价通过TRC-9[危机]难度",
        "needAccept": 1,
        "bonusMail": 0,
        "params": "",
        "openLimit": "",
        "listenerType": "EpisodeStarAdvence",
        "listenerParam": "1120109",
        "maxProgress": 1,
        "maxFinishCount": 1,
        "activity": 1,
        "jumpId": 41120109,
        "bonus": ""
    },
    {
        "id": 110057,
        "activityId": 11104,
        "isOnline": 1,
        "minType": "雷米特杯成就任务",
        "name": "",
        "desc": "2星评价通过TRC-11[危机]难度",
        "needAccept": 1,
        "bonusMail": 0,
        "params": "",
        "openLimit": "",
        "listenerType": "EpisodeStarAdvence",
        "listenerParam": "1120111",
        "maxProgress": 1,
        "maxFinishCount": 1,
        "activity": 1,
        "jumpId": 41120111,
        "bonus": ""
    },
    {
        "id": 110058,
        "activityId": 11104,
        "isOnline": 1,
        "minType": "雷米特杯成就任务",
        "name": "",
        "desc": "2星评价通过TRC-12[危机]难度",
        "needAccept": 1,
        "bonusMail": 0,
        "params": "",
        "openLimit": "",
        "listenerType": "EpisodeStarAdvence",
        "listenerParam": "1120112",
        "maxProgress": 1,
        "maxFinishCount": 1,
        "activity": 1,
        "jumpId": 41120112,
        "bonus": ""
    },
    {
        "id": 110059,
        "activityId": 11104,
        "isOnline": 1,
        "minType": "雷米特杯成就任务",
        "name": "",
        "desc": "2星评价通过TRC-13[危机]难度",
        "needAccept": 1,
        "bonusMail": 0,
        "params": "",
        "openLimit": "",
        "listenerType": "EpisodeStarAdvence",
        "listenerParam": "1120113",
        "maxProgress": 1,
        "maxFinishCount": 1,
        "activity": 1,
        "jumpId": 41120113,
        "bonus": ""
    },
    {
        "id": 110060,
        "activityId": 11104,
        "isOnline": 1,
        "minType": "雷米特杯成就任务",
        "name": "",
        "desc": "2星评价通过TRC-14[危机]难度",
        "needAccept": 1,
        "bonusMail": 0,
        "params": "",
        "openLimit": "",
        "listenerType": "EpisodeStarAdvence",
        "listenerParam": "1120114",
        "maxProgress": 1,
        "maxFinishCount": 1,
        "activity": 1,
        "jumpId": 41120114,
        "bonus": ""
    }
]