[
    {
        "groupId": 100101,
        "id": 1,
        "name": "风车",
        "nameEn": "Windmill",
        "desc": "强化以加快采集效率，占用的繁荣度也会增加",
        "effectType": 0,
        "effect": 0,
        "cost": "",
        "changeFormulaId": "",
        "costResource": 0,
        "modulePart": "collection/plant_1_1#collection/plant_2_1#collection/plant_3_1",
        "icon": "fengche_1"
    },
    {
        "groupId": 100101,
        "id": 2,
        "name": "风车",
        "nameEn": "Windmill",
        "desc": "采集时间减少15%",
        "effectType": 2,
        "effect": 150,
        "cost": "1#190007#1",
        "changeFormulaId": "",
        "costResource": 20,
        "modulePart": "collection/plant_1_2#collection/plant_2_2#collection/plant_3_2",
        "icon": "fengche_2"
    },
    {
        "groupId": 100101,
        "id": 3,
        "name": "风车",
        "nameEn": "Windmill",
        "desc": "采集时间减少25%",
        "effectType": 2,
        "effect": 250,
        "cost": "1#190007#1",
        "changeFormulaId": "",
        "costResource": 50,
        "modulePart": "collection/plant_1_3#collection/plant_2_3#collection/plant_3_3",
        "icon": "fengche_3"
    },
    {
        "groupId": 100201,
        "id": 1,
        "name": "被淹没物",
        "nameEn": "Something Submerged",
        "desc": "强化以加快采集效率，占用的繁荣度也会增加",
        "effectType": 0,
        "effect": 0,
        "cost": "",
        "changeFormulaId": "",
        "costResource": 0,
        "modulePart": "collection/stone_1_1#collection/stone_2_1#collection/stone_3_1",
        "icon": "shijieti_1"
    },
    {
        "groupId": 100201,
        "id": 2,
        "name": "被淹没物",
        "nameEn": "Something Submerged",
        "desc": "采集时间减少15%",
        "effectType": 2,
        "effect": 150,
        "cost": "1#190007#1",
        "changeFormulaId": "",
        "costResource": 20,
        "modulePart": "collection/stone_1_2#collection/stone_2_2#collection/stone_3_2",
        "icon": "shijieti_2"
    },
    {
        "groupId": 100201,
        "id": 3,
        "name": "被淹没物",
        "nameEn": "Something Submerged",
        "desc": "采集时间减少25%",
        "effectType": 2,
        "effect": 250,
        "cost": "1#190007#1",
        "changeFormulaId": "",
        "costResource": 50,
        "modulePart": "collection/stone_1_3#collection/stone_2_3#collection/stone_3_3",
        "icon": "shijieti_3"
    },
    {
        "groupId": 100301,
        "id": 1,
        "name": "需行走者",
        "nameEn": "He Who Shall Walk",
        "desc": "强化以加快采集效率，占用的繁荣度也会增加",
        "effectType": 0,
        "effect": 0,
        "cost": "",
        "changeFormulaId": "",
        "costResource": 0,
        "modulePart": "collection/diaosu_1_1#collection/diaosu_2_1#collection/diaosu_3_1",
        "icon": "daolu_1"
    },
    {
        "groupId": 100301,
        "id": 2,
        "name": "需行走者",
        "nameEn": "He Who Shall Walk",
        "desc": "采集时间减少15%",
        "effectType": 2,
        "effect": 150,
        "cost": "1#190007#1",
        "changeFormulaId": "",
        "costResource": 20,
        "modulePart": "collection/diaosu_1_2#collection/diaosu_2_2#collection/diaosu_3_2",
        "icon": "daolu_2"
    },
    {
        "groupId": 100301,
        "id": 3,
        "name": "需行走者",
        "nameEn": "He Who Shall Walk",
        "desc": "采集时间减少25%",
        "effectType": 2,
        "effect": 250,
        "cost": "1#190007#1",
        "changeFormulaId": "",
        "costResource": 50,
        "modulePart": "collection/diaosu_1_3#collection/diaosu_2_3#collection/diaosu_3_3",
        "icon": "daolu_3"
    },
    {
        "groupId": 100401,
        "id": 1,
        "name": "水上钢琴",
        "nameEn": "Piano on the Water",
        "desc": "强化以加快采集效率，占用的繁荣度也会增加",
        "effectType": 0,
        "effect": 0,
        "cost": "",
        "changeFormulaId": "",
        "costResource": 0,
        "modulePart": "collection/heliu_1_1#collection/heliu_2_1#collection/heliu_3_1",
        "icon": "shuishanggangqin_1"
    },
    {
        "groupId": 100401,
        "id": 2,
        "name": "水上钢琴",
        "nameEn": "Piano on the Water",
        "desc": "采集时间减少15%",
        "effectType": 2,
        "effect": 150,
        "cost": "1#190007#1",
        "changeFormulaId": "",
        "costResource": 20,
        "modulePart": "collection/heliu_1_2#collection/heliu_2_2#collection/heliu_3_2",
        "icon": "shuishanggangqin_2"
    },
    {
        "groupId": 100401,
        "id": 3,
        "name": "水上钢琴",
        "nameEn": "Piano on the Water",
        "desc": "采集时间减少25%",
        "effectType": 2,
        "effect": 250,
        "cost": "1#190007#1",
        "changeFormulaId": "",
        "costResource": 50,
        "modulePart": "collection/heliu_1_3#collection/heliu_2_3#collection/heliu_3_3",
        "icon": "shuishanggangqin_3"
    },
    {
        "groupId": 200101,
        "id": 1,
        "name": "为祭奠一切",
        "nameEn": "To Honor Everything",
        "desc": "强化以增加库存，占用的繁荣度也会增加",
        "effectType": 0,
        "effect": 0,
        "cost": "",
        "changeFormulaId": "",
        "costResource": 0,
        "modulePart": "",
        "icon": "yeyingyingdi_1"
    },
    {
        "groupId": 200101,
        "id": 2,
        "name": "为祭奠一切",
        "nameEn": "To Honor Everything",
        "desc": "增加30库存",
        "effectType": 1,
        "effect": 30,
        "cost": "1#190007#1",
        "changeFormulaId": "",
        "costResource": 5,
        "modulePart": "zhuanhualei/xiuseyingdi_1_1",
        "icon": "yeyingyingdi_1"
    },
    {
        "groupId": 200101,
        "id": 3,
        "name": "为祭奠一切",
        "nameEn": "To Honor Everything",
        "desc": "增加60库存",
        "effectType": 1,
        "effect": 60,
        "cost": "1#190007#1",
        "changeFormulaId": "",
        "costResource": 20,
        "modulePart": "zhuanhualei/xiuseyingdi_1_2",
        "icon": "yeyingyingdi_2"
    },
    {
        "groupId": 200101,
        "id": 4,
        "name": "为祭奠一切",
        "nameEn": "To Honor Everything",
        "desc": "增加100库存",
        "effectType": 1,
        "effect": 100,
        "cost": "1#190007#1",
        "changeFormulaId": "",
        "costResource": 40,
        "modulePart": "zhuanhualei/xiuseyingdi_1_3",
        "icon": "yeyingyingdi_3"
    },
    {
        "groupId": 200102,
        "id": 1,
        "name": "为悼念一切",
        "nameEn": "To Commemorate Everything",
        "desc": "减少生产时间，占用的繁荣度也会增加",
        "effectType": 0,
        "effect": 0,
        "cost": "",
        "changeFormulaId": "",
        "costResource": 0,
        "modulePart": "",
        "icon": "shibiao_1"
    },
    {
        "groupId": 200102,
        "id": 2,
        "name": "为悼念一切",
        "nameEn": "To Commemorate Everything",
        "desc": "减少5%生产时间",
        "effectType": 2,
        "effect": 50,
        "cost": "1#190007#1",
        "changeFormulaId": "",
        "costResource": 0,
        "modulePart": "zhuanhualei/xiuseyingdi_2_1",
        "icon": "shibiao_1"
    },
    {
        "groupId": 200102,
        "id": 3,
        "name": "为悼念一切",
        "nameEn": "To Commemorate Everything",
        "desc": "减少10%生产时间",
        "effectType": 2,
        "effect": 100,
        "cost": "1#190007#1",
        "changeFormulaId": "",
        "costResource": 0,
        "modulePart": "zhuanhualei/xiuseyingdi_2_2",
        "icon": "shibiao_2"
    },
    {
        "groupId": 200102,
        "id": 4,
        "name": "为悼念一切",
        "nameEn": "To Commemorate Everything",
        "desc": "减少15%生产时间",
        "effectType": 2,
        "effect": 150,
        "cost": "1#190007#1",
        "changeFormulaId": "",
        "costResource": 0,
        "modulePart": "zhuanhualei/xiuseyingdi_2_3",
        "icon": "shibiao_3"
    },
    {
        "groupId": 200201,
        "id": 0,
        "name": "池塘",
        "nameEn": "Pond",
        "desc": "强化以减少采集时间，占用的繁荣度也会增加",
        "effectType": 0,
        "effect": 0,
        "cost": "",
        "changeFormulaId": "",
        "costResource": 0,
        "modulePart": "changchulei/jingyanshu_1_1#changchulei/jingyanshu_3_1",
        "icon": "chitang_1"
    },
    {
        "groupId": 200201,
        "id": 1,
        "name": "池塘",
        "nameEn": "Pond",
        "desc": "减少10%生产时间",
        "effectType": 2,
        "effect": 100,
        "cost": "1#190007#1",
        "changeFormulaId": "",
        "costResource": 20,
        "modulePart": "changchulei/jingyanshu_1_2#changchulei/jingyanshu_3_2",
        "icon": "chitang_2"
    },
    {
        "groupId": 200201,
        "id": 2,
        "name": "池塘",
        "nameEn": "Pond",
        "desc": "减少20%生产时间",
        "effectType": 2,
        "effect": 200,
        "cost": "1#190007#1",
        "changeFormulaId": "",
        "costResource": 40,
        "modulePart": "changchulei/jingyanshu_1_3#changchulei/jingyanshu_3_3",
        "icon": "chitang_3"
    },
    {
        "groupId": 200202,
        "id": 0,
        "name": "庭院",
        "nameEn": "Lighted Path",
        "desc": "强化以增加采集速度和库存，占用的繁荣度也会增加",
        "effectType": 0,
        "effect": 0,
        "cost": "",
        "changeFormulaId": "",
        "costResource": 0,
        "modulePart": "",
        "icon": "tingyuan_1"
    },
    {
        "groupId": 200202,
        "id": 1,
        "name": "庭院",
        "nameEn": "Lighted Path",
        "desc": "增加采集速度并扩大1040库存",
        "effectType": 1,
        "effect": 1040,
        "cost": "1#190007#1",
        "changeFormulaId": "2002002",
        "costResource": 5,
        "modulePart": "changchulei/jingyanshu_2_1",
        "icon": "tingyuan_1"
    },
    {
        "groupId": 200202,
        "id": 2,
        "name": "庭院",
        "nameEn": "Lighted Path",
        "desc": "增加采集速度并扩大2300库存",
        "effectType": 1,
        "effect": 2300,
        "cost": "1#190007#1",
        "changeFormulaId": "2002003",
        "costResource": 20,
        "modulePart": "changchulei/jingyanshu_2_1",
        "icon": "tingyuan_1"
    },
    {
        "groupId": 200202,
        "id": 3,
        "name": "庭院",
        "nameEn": "Lighted Path",
        "desc": "增加采集速度并扩大4300库存",
        "effectType": 1,
        "effect": 4300,
        "cost": "1#190007#1",
        "changeFormulaId": "2002004",
        "costResource": 35,
        "modulePart": "changchulei/jingyanshu_2_2",
        "icon": "tingyuan_2"
    },
    {
        "groupId": 210101,
        "id": 0,
        "name": "为祭奠一切",
        "nameEn": "To Honor Everything",
        "desc": "强化以减少采集时间，占用的繁荣度也会增加",
        "effectType": 0,
        "effect": 0,
        "cost": "",
        "changeFormulaId": "",
        "costResource": 0,
        "modulePart": "zhuanhualei/xiuseyingdi_1_1",
        "icon": "yeyingyingdi_1"
    },
    {
        "groupId": 210101,
        "id": 1,
        "name": "为祭奠一切",
        "nameEn": "To Honor Everything",
        "desc": "减少10%生产时间",
        "effectType": 2,
        "effect": 100,
        "cost": "1#190007#1",
        "changeFormulaId": "",
        "costResource": 20,
        "modulePart": "zhuanhualei/xiuseyingdi_1_2",
        "icon": "yeyingyingdi_2"
    },
    {
        "groupId": 210101,
        "id": 2,
        "name": "为祭奠一切",
        "nameEn": "To Honor Everything",
        "desc": "减少20%生产时间",
        "effectType": 2,
        "effect": 200,
        "cost": "1#190007#1",
        "changeFormulaId": "",
        "costResource": 40,
        "modulePart": "zhuanhualei/xiuseyingdi_1_3",
        "icon": "yeyingyingdi_3"
    },
    {
        "groupId": 210102,
        "id": 0,
        "name": "为悼念一切",
        "nameEn": "To Commemorate Everything",
        "desc": "强化以增加采集速度和库存，占用的繁荣度也会增加",
        "effectType": 0,
        "effect": 0,
        "cost": "",
        "changeFormulaId": "",
        "costResource": 0,
        "modulePart": "",
        "icon": "shibiao_1"
    },
    {
        "groupId": 210102,
        "id": 1,
        "name": "为悼念一切",
        "nameEn": "To Commemorate Everything",
        "desc": "增加采集速度并扩大1000库存",
        "effectType": 1,
        "effect": 1000,
        "cost": "1#190007#1",
        "changeFormulaId": "2101002",
        "costResource": 5,
        "modulePart": "zhuanhualei/xiuseyingdi_2_1",
        "icon": "shibiao_1"
    },
    {
        "groupId": 210102,
        "id": 2,
        "name": "为悼念一切",
        "nameEn": "To Commemorate Everything",
        "desc": "增加采集速度并扩大1150库存",
        "effectType": 1,
        "effect": 1150,
        "cost": "1#190007#1",
        "changeFormulaId": "2101003",
        "costResource": 20,
        "modulePart": "zhuanhualei/xiuseyingdi_2_2",
        "icon": "shibiao_2"
    },
    {
        "groupId": 210102,
        "id": 3,
        "name": "为悼念一切",
        "nameEn": "To Commemorate Everything",
        "desc": "增加采集速度并扩大4000库存",
        "effectType": 1,
        "effect": 4000,
        "cost": "1#190007#1",
        "changeFormulaId": "2101004",
        "costResource": 35,
        "modulePart": "zhuanhualei/xiuseyingdi_2_3",
        "icon": "shibiao_3"
    },
    {
        "groupId": 200301,
        "id": 0,
        "name": "可攀登的",
        "nameEn": "The Climbable",
        "desc": "解锁雨滴订单，升级更高收益订单占用的繁荣度也会增加",
        "effectType": 0,
        "effect": 0,
        "cost": "",
        "changeFormulaId": "",
        "costResource": 0,
        "modulePart": "",
        "icon": "tizi_1"
    },
    {
        "groupId": 200301,
        "id": 1,
        "name": "可攀登的",
        "nameEn": "The Climbable",
        "desc": "解锁雨滴订单",
        "effectType": 0,
        "effect": 0,
        "cost": "1#190007#1",
        "changeFormulaId": "2003001#2003101",
        "costResource": 5,
        "modulePart": "jiaoyilei/yuanfanglouge_2_1",
        "icon": "tizi_1"
    },
    {
        "groupId": 200301,
        "id": 2,
        "name": "可攀登的",
        "nameEn": "The Climbable",
        "desc": "解锁更高级金币订单",
        "effectType": 0,
        "effect": 0,
        "cost": "1#190007#1",
        "changeFormulaId": "2003002#2003101",
        "costResource": 15,
        "modulePart": "jiaoyilei/yuanfanglouge_2_1",
        "icon": "tizi_1"
    },
    {
        "groupId": 200301,
        "id": 3,
        "name": "可攀登的",
        "nameEn": "The Climbable",
        "desc": "解锁更高级雨滴订单",
        "effectType": 0,
        "effect": 0,
        "cost": "1#190007#1",
        "changeFormulaId": "2003002#2003102",
        "costResource": 25,
        "modulePart": "jiaoyilei/yuanfanglouge_2_2",
        "icon": "tizi_2"
    },
    {
        "groupId": 200301,
        "id": 4,
        "name": "可攀登的",
        "nameEn": "The Climbable",
        "desc": "解锁更高级金币订单",
        "effectType": 0,
        "effect": 0,
        "cost": "1#190007#1",
        "changeFormulaId": "2003003#2003102",
        "costResource": 40,
        "modulePart": "jiaoyilei/yuanfanglouge_2_2",
        "icon": "tizi_2"
    },
    {
        "groupId": 200301,
        "id": 5,
        "name": "可攀登的",
        "nameEn": "The Climbable",
        "desc": "解锁更高级雨滴订单",
        "effectType": 0,
        "effect": 0,
        "cost": "1#190007#1",
        "changeFormulaId": "2003003#2003103",
        "costResource": 60,
        "modulePart": "jiaoyilei/yuanfanglouge_2_3",
        "icon": "tizi_3"
    },
    {
        "groupId": 200302,
        "id": 0,
        "name": "可遗忘的",
        "nameEn": "The Forgettable",
        "desc": "减少订单寻找时间，占用的繁荣度也会增加",
        "effectType": 0,
        "effect": 0,
        "cost": "",
        "changeFormulaId": "",
        "costResource": 0,
        "modulePart": "",
        "icon": "xvanfuwu_1"
    },
    {
        "groupId": 200302,
        "id": 1,
        "name": "可遗忘的",
        "nameEn": "The Forgettable",
        "desc": "减少5%订单寻找时间",
        "effectType": 2,
        "effect": 50,
        "cost": "1#190007#1",
        "changeFormulaId": "",
        "costResource": 5,
        "modulePart": "jiaoyilei/yuanfanglouge_1_1",
        "icon": "xvanfuwu_1"
    },
    {
        "groupId": 200302,
        "id": 2,
        "name": "可遗忘的",
        "nameEn": "The Forgettable",
        "desc": "减少10%订单寻找时间",
        "effectType": 2,
        "effect": 100,
        "cost": "1#190007#1",
        "changeFormulaId": "",
        "costResource": 20,
        "modulePart": "jiaoyilei/yuanfanglouge_1_2",
        "icon": "xvanfuwu_2"
    },
    {
        "groupId": 200302,
        "id": 3,
        "name": "可遗忘的",
        "nameEn": "The Forgettable",
        "desc": "减少15%订单寻找时间",
        "effectType": 2,
        "effect": 150,
        "cost": "1#190007#1",
        "changeFormulaId": "",
        "costResource": 40,
        "modulePart": "jiaoyilei/yuanfanglouge_1_3",
        "icon": "xvanfuwu_3"
    },
    {
        "groupId": 200303,
        "id": 0,
        "name": "可穿行的",
        "nameEn": "The Passable",
        "desc": "强化以增加订单栏位，占用的繁荣度也会增加",
        "effectType": 0,
        "effect": 0,
        "cost": "",
        "changeFormulaId": "",
        "costResource": 0,
        "modulePart": "",
        "icon": "gongmen_1"
    },
    {
        "groupId": 200303,
        "id": 1,
        "name": "可穿行的",
        "nameEn": "The Passable",
        "desc": "额外增加2个订单栏位",
        "effectType": 1,
        "effect": 2,
        "cost": "1#190007#1",
        "changeFormulaId": "",
        "costResource": 5,
        "modulePart": "jiaoyilei/yuanfanglouge_3_1",
        "icon": "gongmen_1"
    },
    {
        "groupId": 200303,
        "id": 2,
        "name": "可穿行的",
        "nameEn": "The Passable",
        "desc": "额外增加4个订单栏位",
        "effectType": 1,
        "effect": 4,
        "cost": "1#190007#1",
        "changeFormulaId": "",
        "costResource": 20,
        "modulePart": "jiaoyilei/yuanfanglouge_3_2",
        "icon": "gongmen_2"
    },
    {
        "groupId": 200303,
        "id": 3,
        "name": "可穿行的",
        "nameEn": "The Passable",
        "desc": "额外增加6个订单栏位",
        "effectType": 1,
        "effect": 6,
        "cost": "1#190007#1",
        "changeFormulaId": "",
        "costResource": 40,
        "modulePart": "jiaoyilei/yuanfanglouge_3_3",
        "icon": "gongmen_3"
    }
]